casm/__init__.py
casm/attribute.py
casm/cmds/__init__.py
casm/cmds/casm.py
casm/cmds/cman.py
casm/cmds/modify/__init__.py
casm/cmds/modify/assemble.py
casm/cmds/modify/template.py
casm/cmds/podman/__init__.py
casm/cmds/podman/container.py
casm/cmds/podman/guard.py
casm/cmds/podman/system.py
casm/cmds/podman_compose/__init__.py
casm/cmds/podman_compose/down.py
casm/cmds/podman_compose/exec.py
casm/cmds/podman_compose/logs.py
casm/cmds/podman_compose/pause.py
casm/cmds/podman_compose/pull.py
casm/cmds/podman_compose/restart.py
casm/cmds/podman_compose/service.py
casm/cmds/podman_compose/start.py
casm/cmds/podman_compose/stop.py
casm/cmds/podman_compose/systemd.py
casm/cmds/podman_compose/unpause.py
casm/cmds/podman_compose/up.py
casm/utils/__init__.py
casm/utils/assemble.py
casm/utils/common.py
casm/utils/compose.py
casm/utils/podman.py
casm/utils/podman_compose.py
casm/utils/yaml.py
casm-0.10.3.dist-info/LICENSE
casm-0.10.3.dist-info/METADATA
casm-0.10.3.dist-info/WHEEL
casm-0.10.3.dist-info/entry_points.txt
casm-0.10.3.dist-info/top_level.txt
casm-0.10.3.dist-info/zip-safe
casm-0.10.3.dist-info/RECORD
